cartopy/__init__.py
cartopy/_epsg.py
cartopy/_version.py
cartopy/crs.py
cartopy/geodesic.py
cartopy/img_transform.py
cartopy/trace.cp313-win_amd64.pyd
cartopy/trace.cpp
cartopy/trace.pyx
cartopy/util.py
cartopy/vector_transform.py
cartopy/data/LICENSE
cartopy/data/netcdf/HadISST1_SST_update.README.txt
cartopy/data/netcdf/HadISST1_SST_update.nc
cartopy/data/raster/natural_earth/50-natural-earth-1-downsampled.png
cartopy/data/raster/natural_earth/images.json
cartopy/data/raster/sample/Miriam.A2012270.2050.2km.README.txt
cartopy/data/raster/sample/Miriam.A2012270.2050.2km.jpg
cartopy/feature/__init__.py
cartopy/feature/nightshade.py
cartopy/feature/download/__main__.py
cartopy/io/__init__.py
cartopy/io/img_nest.py
cartopy/io/img_tiles.py
cartopy/io/ogc_clients.py
cartopy/io/shapereader.py
cartopy/io/srtm.npz
cartopy/io/srtm.py
cartopy/mpl/__init__.py
cartopy/mpl/clip_path.py
cartopy/mpl/contour.py
cartopy/mpl/feature_artist.py
cartopy/mpl/geoaxes.py
cartopy/mpl/geocollection.py
cartopy/mpl/gridliner.py
cartopy/mpl/patch.py
cartopy/mpl/path.py
cartopy/mpl/slippy_image_artist.py
cartopy/mpl/style.py
cartopy/mpl/ticker.py
cartopy/tests/__init__.py
cartopy/tests/conftest.py
cartopy/tests/test_coastline.py
cartopy/tests/test_coding_standards.py
cartopy/tests/test_crs.py
cartopy/tests/test_crs_transform_vectors.py
cartopy/tests/test_features.py
cartopy/tests/test_geodesic.py
cartopy/tests/test_img_nest.py
cartopy/tests/test_img_tiles.py
cartopy/tests/test_img_transform.py
cartopy/tests/test_line_string.py
cartopy/tests/test_linear_ring.py
cartopy/tests/test_polygon.py
cartopy/tests/test_shapereader.py
cartopy/tests/test_util.py
cartopy/tests/test_vector_transform.py
cartopy/tests/crs/__init__.py
cartopy/tests/crs/helpers.py
cartopy/tests/crs/test_aitoff.py
cartopy/tests/crs/test_albers_equal_area.py
cartopy/tests/crs/test_azimuthal_equidistant.py
cartopy/tests/crs/test_eckert.py
cartopy/tests/crs/test_equal_earth.py
cartopy/tests/crs/test_equidistant_conic.py
cartopy-0.25.0.dist-info/licenses/LICENSE
cartopy-0.25.0.dist-info/METADATA
cartopy-0.25.0.dist-info/WHEEL
cartopy-0.25.0.dist-info/entry_points.txt
cartopy-0.25.0.dist-info/top_level.txt
cartopy-0.25.0.dist-info/RECORD
