Metadata-Version: 2.4
Name: Cartopy
Version: 0.25.0
Summary: A Python library for cartographic visualizations with Matplotlib
Author: UK Met Office
License-Expression: BSD-3-Clause
Project-URL: documentation, https://scitools.org.uk/cartopy/docs/latest/
Project-URL: homepage, https://github.com/SciTools/cartopy
Keywords: cartography,map,transform,projection,pyproj,shapely,shapefile
Classifier: Development Status :: 4 - Beta
Classifier: Framework :: Matplotlib
Classifier: Operating System :: MacOS :: MacOS X
Classifier: Operating System :: Microsoft :: Windows
Classifier: Operating System :: POSIX
Classifier: Operating System :: POSIX :: AIX
Classifier: Operating System :: POSIX :: Linux
Classifier: Programming Language :: C++
Classifier: Programming Language :: Python
Classifier: Programming Language :: Python :: 3
Classifier: Programming Language :: Python :: 3.10
Classifier: Programming Language :: Python :: 3.11
Classifier: Programming Language :: Python :: 3.12
Classifier: Programming Language :: Python :: 3 :: Only
Classifier: Topic :: Scientific/Engineering
Classifier: Topic :: Scientific/Engineering :: GIS
Classifier: Topic :: Scientific/Engineering :: Visualization
Requires-Python: >=3.10
License-File: LICENSE
Requires-Dist: numpy>=1.23
Requires-Dist: matplotlib>=3.6
Requires-Dist: shapely>=2.0
Requires-Dist: packaging>=21
Requires-Dist: pyshp>=2.3
Requires-Dist: pyproj>=3.3.1
Provides-Extra: doc
Requires-Dist: pydata-sphinx-theme; extra == "doc"
Requires-Dist: sphinx; extra == "doc"
Requires-Dist: sphinx-gallery; extra == "doc"
Provides-Extra: speedups
Requires-Dist: pykdtree; extra == "speedups"
Requires-Dist: fiona; extra == "speedups"
Provides-Extra: ows
Requires-Dist: OWSLib>=0.27.0; extra == "ows"
Requires-Dist: pillow>=9.1; extra == "ows"
Provides-Extra: plotting
Requires-Dist: pillow>=9.1; extra == "plotting"
Requires-Dist: scipy>=1.9; extra == "plotting"
Provides-Extra: srtm
Requires-Dist: beautifulsoup4; extra == "srtm"
Provides-Extra: test
Requires-Dist: pytest>=5.1.2; extra == "test"
Requires-Dist: pytest-mpl>=0.11; extra == "test"
Requires-Dist: pytest-xdist; extra == "test"
Requires-Dist: pytest-cov; extra == "test"
Requires-Dist: coveralls; extra == "test"
Dynamic: license-file
